f5_sphinx_theme/__init__.py
f5_sphinx_theme/breadcrumb.html
f5_sphinx_theme/extralinks.html
f5_sphinx_theme/globaltoc.html
f5_sphinx_theme/head.html
f5_sphinx_theme/layout.html
f5_sphinx_theme/localtoc.html
f5_sphinx_theme/searchbox.html
f5_sphinx_theme/theme.conf
f5_sphinx_theme/static/css/CoveoFullSearch.css
f5_sphinx_theme/static/css/bootstrap-theme.css
f5_sphinx_theme/static/css/bootstrap-theme.min.css
f5_sphinx_theme/static/css/bootstrap.css
f5_sphinx_theme/static/css/bootstrap.min.css
f5_sphinx_theme/static/css/custom.css
f5_sphinx_theme/static/css/f5-theme.css
f5_sphinx_theme/static/css/f5.css
f5_sphinx_theme/static/fonts/ProximaBold.woff
f5_sphinx_theme/static/fonts/ProximaBold.woff2
f5_sphinx_theme/static/fonts/ProximaMedium.woff
f5_sphinx_theme/static/fonts/ProximaMedium.woff2
f5_sphinx_theme/static/fonts/ProximaThin.woff
f5_sphinx_theme/static/fonts/ProximaThin.woff2
f5_sphinx_theme/static/fonts/glyphicons-halflings-regular.eot
f5_sphinx_theme/static/fonts/glyphicons-halflings-regular.svg
f5_sphinx_theme/static/fonts/glyphicons-halflings-regular.ttf
f5_sphinx_theme/static/fonts/glyphicons-halflings-regular.woff
f5_sphinx_theme/static/fonts/glyphicons-halflings-regular.woff2
f5_sphinx_theme/static/js/CoveoJsSearch.Lazy.min.js
f5_sphinx_theme/static/js/bootstrap.js
f5_sphinx_theme/static/js/bootstrap.min.js
f5_sphinx_theme/static/js/clouddocs.js
f5_sphinx_theme/static/js/feedback.js
f5_sphinx_theme/static/js/jquery.appear.js
f5_sphinx_theme/static/js/printThis.js
f5_sphinx_theme-2.9.2.dist-info/LICENSE
f5_sphinx_theme-2.9.2.dist-info/METADATA
f5_sphinx_theme-2.9.2.dist-info/WHEEL
f5_sphinx_theme-2.9.2.dist-info/entry_points.txt
f5_sphinx_theme-2.9.2.dist-info/top_level.txt
f5_sphinx_theme-2.9.2.dist-info/RECORD
