Metadata-Version: 2.1
Name: f5-sphinx-theme
Version: 2.9.2
Summary: Sphinx theme for F5 Networks
Home-page: https://github.com/F5DevCentral/f5-sphinx-theme
Author: F5 Networks
Author-email: f5-sphinx-theme@f5.com
License: Apache2
Classifier: Framework :: Sphinx
Classifier: Framework :: Sphinx :: Theme
Classifier: Development Status :: 5 - Production/Stable
Classifier: License :: OSI Approved :: Apache Software License
Classifier: Environment :: Console
Classifier: Environment :: Web Environment
Classifier: Intended Audience :: Developers
Classifier: Programming Language :: Python :: 2.7
Classifier: Operating System :: OS Independent
Classifier: Topic :: Documentation
Classifier: Topic :: Software Development :: Documentation
Requires-Python: >=2.7, !=3.0.*, !=3.1.*, !=3.2.*, !=3.3.*
License-File: LICENSE
